<?xml version="1.0" encoding="utf-8" standalone="no"?>
<!DOCTYPE paula SYSTEM "paula_mark.dtd">
<paula version="1.0">
<header paula_id="mycorpus.adam_line"/>
<markList xmlns:xlink="http://www.w3.org/1999/xlink" type="line" xml:base="mycorpus.adam.tok.xml">
<mark id="line_0" xlink:href="#xpointer(id('tok_0')/range-to(id('tok_13')))"/><!-- adamCVsireVCefourméVCVteeai -->
<mark id="line_1" xlink:href="#xpointer(id('tok_14')/range-to(id('tok_21')))"/><!-- deebenVleesaiV -->
<mark id="line_2" xlink:href="#xpointer(id('tok_22')/range-to(id('tok_37')))"/><!-- jeeteeaifourméVCVamunVsemblantVCV -->
<mark id="line_3" xlink:href="#xpointer(id('tok_38')/range-to(id('tok_55')))"/><!-- amaVimageneCVCetaifeitVdeeterreVCe -->
<mark id="line_4" xlink:href="#xpointer(id('tok_56')/range-to(id('tok_75')))"/><!-- neemoiVdevezVCVjaVmaisVmoverVCVguereVCe -->
<mark id="line_5" xlink:href="#xpointer(id('tok_76')/range-to(id('tok_89')))"/><!-- nenVfraiVgeemaisVteecrerraiVCV -->
<mark id="line_6" xlink:href="#xpointer(id('tok_90')/range-to(id('tok_103')))"/><!-- munVcreaturVCVCVoberaiCVVCV -->
<mark id="line_7" xlink:href="#xpointer(id('tok_104')/range-to(id('tok_119')))"/><!-- jeetaidunéVCVbonVcumpainunVCVCV -->
<mark id="line_8" xlink:href="#xpointer(id('tok_120')/range-to(id('tok_134')))"/><!-- ceeesttaVfemmeVCeevaCeanounV -->
<mark id="line_9" xlink:href="#xpointer(id('tok_135')/range-to(id('tok_150')))"/><!-- ceeesttaVfemmeVCeetunVpareilVCV -->
<mark id="line_10" xlink:href="#xpointer(id('tok_151')/range-to(id('tok_165')))"/><!-- tuVleedevezVCVestreCebenVfielV -->
<mark id="line_11" xlink:href="#xpointer(id('tok_166')/range-to(id('tok_181')))"/><!-- tuVaimeCeluiVeeleCeameCeteiV -->
<mark id="line_12" xlink:href="#xpointer(id('tok_182')/range-to(id('tok_198')))"/><!-- siVserezVCVbenVambeduiCeCVdeemoiV -->
<mark id="line_13" xlink:href="#xpointer(id('tok_199')/range-to(id('tok_214')))"/><!-- eleCesoitVatunVcomandementVCVCeCV -->
<mark id="line_14" xlink:href="#xpointer(id('tok_215')/range-to(id('tok_229')))"/><!-- evusVambedeusCeCVamunVtalentVCV -->
<mark id="line_15" xlink:href="#xpointer(id('tok_230')/range-to(id('tok_244')))"/><!-- deetaVcosteVCel'aifourmeeVCVe -->
<mark id="line_16" xlink:href="#xpointer(id('tok_245')/range-to(id('tok_261')))"/><!-- nestpasVestrangeCVCedeeteiVestneeVe -->
<mark id="line_17" xlink:href="#xpointer(id('tok_262')/range-to(id('tok_275')))"/><!-- joVlaVplasmaiVCVdeetonVcorsV -->
<mark id="line_18" xlink:href="#xpointer(id('tok_276')/range-to(id('tok_290')))"/><!-- deeteiVeissitCVnonVpasVdeeforsV -->
<mark id="line_19" xlink:href="#xpointer(id('tok_291')/range-to(id('tok_306')))"/><!-- tuVlaVgoverneVCVCeparVraisonVCV -->
<mark id="line_20" xlink:href="#xpointer(id('tok_307')/range-to(id('tok_319')))"/><!-- naitentreCevusVjaVtenconVCV -->
<mark id="line_21" xlink:href="#xpointer(id('tok_320')/range-to(id('tok_336')))"/><!-- maisVgrantVamorCVgrantVconservageVCVCVCe -->
<mark id="line_22" xlink:href="#xpointer(id('tok_337')/range-to(id('tok_354')))"/><!-- telVsoitVlaVleiVdeemariageVCVCVCe -->
<mark id="line_23" xlink:href="#xpointer(id('tok_355')/range-to(id('tok_366')))"/><!-- ateiVparleraiVCeCVevainCV -->
<mark id="line_24" xlink:href="#xpointer(id('tok_367')/range-to(id('tok_384')))"/><!-- coVgardeVCetuVneel'tenezVCVenvainV -->
<mark id="line_25" xlink:href="#xpointer(id('tok_385')/range-to(id('tok_400')))"/><!-- siVvosVfaireVCemaVvolentéVCVCV -->
<mark id="line_26" xlink:href="#xpointer(id('tok_401')/range-to(id('tok_415')))"/><!-- entonVcorsVgarderasVCeCVbontéVCV -->
<mark id="line_27" xlink:href="#xpointer(id('tok_416')/range-to(id('tok_428')))"/><!-- aimethonorCVtonVcreatorVCVCV -->
<mark id="line_28" xlink:href="#xpointer(id('tok_429')/range-to(id('tok_442')))"/><!-- emoiVreconuisVCVCVaseignorVCV -->
<mark id="line_29" xlink:href="#xpointer(id('tok_443')/range-to(id('tok_457')))"/><!-- amoiVservirVCVmetVtonVporpensVCV -->
<mark id="line_30" xlink:href="#xpointer(id('tok_458')/range-to(id('tok_472')))"/><!-- tutVtaVforceVCeetotVtunVsensV -->
<mark id="line_31" xlink:href="#xpointer(id('tok_473')/range-to(id('tok_485')))"/><!-- adamCVaimeCeetluiVtienVchierV -->
<mark id="line_32" xlink:href="#xpointer(id('tok_486')/range-to(id('tok_500')))"/><!-- ilestmaridVCVetuVsaVmullierVCV -->
<mark id="line_33" xlink:href="#xpointer(id('tok_501')/range-to(id('tok_515')))"/><!-- aluiVsoiesVetotVtensVenclineCVCe -->
<mark id="line_34" xlink:href="#xpointer(id('tok_516')/range-to(id('tok_532')))"/><!-- nenVissirCVdeesaVdisciplineVCVCVCe -->
<mark id="line_35" xlink:href="#xpointer(id('tok_533')/range-to(id('tok_548')))"/><!-- luiVserfVeaimparVbonVcorajeVCVCe -->
<mark id="line_36" xlink:href="#xpointer(id('tok_549')/range-to(id('tok_565')))"/><!-- carVcoVestdroizVdeemariageVCVCVCe -->
<mark id="line_37" xlink:href="#xpointer(id('tok_566')/range-to(id('tok_582')))"/><!-- seetuVleefaisVbonVadjutoireCVCVCe -->
<mark id="line_38" xlink:href="#xpointer(id('tok_583')/range-to(id('tok_598')))"/><!-- joVteemettraiVCVodluiVengloireVCe -->
<mark id="line_39" xlink:href="#xpointer(id('tok_599')/range-to(id('tok_614')))"/><!-- joVl'fraiVsireVCeatonVplaisirVCV -->
<mark id="line_40" xlink:href="#xpointer(id('tok_615')/range-to(id('tok_629')))"/><!-- jaVnenvoldraiVCVdeerienVissirCV -->
<mark id="line_41" xlink:href="#xpointer(id('tok_630')/range-to(id('tok_642')))"/><!-- toiVconustraiVCVCVaseignorVCV -->
<mark id="line_42" xlink:href="#xpointer(id('tok_643')/range-to(id('tok_657')))"/><!-- luiVaparailleVCVCeetaforzorVCV -->
<mark id="line_43" xlink:href="#xpointer(id('tok_658')/range-to(id('tok_672')))"/><!-- joVluiVserraiVCVtotVtensVfeelVV -->
<mark id="line_44" xlink:href="#xpointer(id('tok_673')/range-to(id('tok_685')))"/><!-- deemoiVavraCVbonVconseilVCV -->
<mark id="line_45" xlink:href="#xpointer(id('tok_686')/range-to(id('tok_703')))"/><!-- leetonVpleisirVCVleetonVserviseVCVCe -->
<mark id="line_46" xlink:href="#xpointer(id('tok_704')/range-to(id('tok_718')))"/><!-- fraiVsireVCeentoteVCeguiseVCe -->
<mark id="line_47" xlink:href="#xpointer(id('tok_719')/range-to(id('tok_733')))"/><!-- joVsaiVcomentVCVemoiVqueechaltV -->
<mark id="line_48" xlink:href="#xpointer(id('tok_734')/range-to(id('tok_747')))"/><!-- porVqueiVnonVrienVneemeevaltV -->
<mark id="line_49" xlink:href="#xpointer(id('tok_748')/range-to(id('tok_762')))"/><!-- ilteevaldraVCVjoVneesaiVquantV -->
<mark id="line_50" xlink:href="#xpointer(id('tok_763')/range-to(id('tok_778')))"/><!-- neel'teedirraiVCVpasVencurantVCV -->
<mark id="line_51" xlink:href="#xpointer(id('tok_779')/range-to(id('tok_791')))"/><!-- orleemeediVnonVfraiVpasV -->
<mark id="line_52" xlink:href="#xpointer(id('tok_792')/range-to(id('tok_805')))"/><!-- ainzteeverraiVCVdelVpreerVVlasV -->
<mark id="line_53" xlink:href="#xpointer(id('tok_806')/range-to(id('tok_821')))"/><!-- nainulVbosoingVCVdeecoVsaveirVCV -->
<mark id="line_54" xlink:href="#xpointer(id('tok_822')/range-to(id('tok_836')))"/><!-- karVtuVneedeizVnulVbienVaverCV -->
<mark id="line_55" xlink:href="#xpointer(id('tok_837')/range-to(id('tok_853')))"/><!-- tuVasliVbienVneeseiezVCVjoirVCV -->
<mark id="line_56" xlink:href="#xpointer(id('tok_854')/range-to(id('tok_868')))"/><!-- ejoVcomentVCVvoldrasVCVl'oïrCV -->
<mark id="line_57" xlink:href="#xpointer(id('tok_869')/range-to(id('tok_885')))"/><!-- joVl'teedirraiVCVpriveementVCVCeCV -->
<mark id="line_58" xlink:href="#xpointer(id('tok_886')/range-to(id('tok_892')))"/><!-- seurementVVCeCV -->
<mark id="line_59" xlink:href="#xpointer(id('tok_893')/range-to(id('tok_904')))"/><!-- escultCVadamCVententCVamoiV -->
<mark id="line_60" xlink:href="#xpointer(id('tok_905')/range-to(id('tok_918')))"/><!-- coVierttonVpruVejoVl'otreiCV -->
<mark id="line_61" xlink:href="#xpointer(id('tok_919')/range-to(id('tok_932')))"/><!-- creraseCVmeetuVoïlVmultVbienV -->
<mark id="line_62" xlink:href="#xpointer(id('tok_933')/range-to(id('tok_948')))"/><!-- delVtutVentutVforsVdeeuneCerienV -->
<mark id="line_63" xlink:href="#xpointer(id('tok_949')/range-to(id('tok_965')))"/><!-- deequelVchoseVCejoVl'teedirraiVCV -->
<mark id="line_64" xlink:href="#xpointer(id('tok_966')/range-to(id('tok_982')))"/><!-- monVcreatorVCVCVpasVneeoffendraiCVCV -->
<mark id="line_65" xlink:href="#xpointer(id('tok_983')/range-to(id('tok_996')))"/><!-- criensVleetuVtantVoïlVparVveirV -->
<mark id="line_66" xlink:href="#xpointer(id('tok_997')/range-to(id('tok_1011')))"/><!-- joVl'aimecriemVnestpasVsaveirVCV -->
<mark id="line_67" xlink:href="#xpointer(id('tok_1012')/range-to(id('tok_1027')))"/><!-- queeteepoetVfaireVCeebienVemalV -->
<mark id="line_68" xlink:href="#xpointer(id('tok_1028')/range-to(id('tok_1040')))"/><!-- moltVesentréCVenfolVjornalVCV -->
<mark id="line_69" xlink:href="#xpointer(id('tok_1041')/range-to(id('tok_1058')))"/><!-- quantVcreiezVCVmalVteepoisseVCevenirVCV -->
<mark id="line_70" xlink:href="#xpointer(id('tok_1059')/range-to(id('tok_1077')))"/><!-- nestuVengloireVCenenVpoezVCVmorirVCV -->
<mark id="line_71" xlink:href="#xpointer(id('tok_1078')/range-to(id('tok_1093')))"/><!-- deusVleem'aditVqueejeemurraiVCV -->
<mark id="line_72" xlink:href="#xpointer(id('tok_1094')/range-to(id('tok_1109')))"/><!-- quantVsonVpreceptVCVtrespasseraiVCVCeCV -->
<mark id="line_73" xlink:href="#xpointer(id('tok_1110')/range-to(id('tok_1124')))"/><!-- quelVestcistVgrantVtrespassementVCVCeCV -->
<mark id="line_74" xlink:href="#xpointer(id('tok_1125')/range-to(id('tok_1138')))"/><!-- oïrCVleevoilVsensVnulVententCV -->
<mark id="line_75" xlink:href="#xpointer(id('tok_1139')/range-to(id('tok_1155')))"/><!-- joVl'teedirraiVCVtotVveirementVCeCV -->
<mark id="line_76" xlink:href="#xpointer(id('tok_1156')/range-to(id('tok_1169')))"/><!-- ilmeefistVuncomandementVCVCeCV -->
<mark id="line_77" xlink:href="#xpointer(id('tok_1170')/range-to(id('tok_1185')))"/><!-- deetuitVleefruitVdeeparadisVCVCV -->
<mark id="line_78" xlink:href="#xpointer(id('tok_1186')/range-to(id('tok_1200')))"/><!-- puisVjoVmangerVCVcoVm'aaprisCV -->
<mark id="line_79" xlink:href="#xpointer(id('tok_1201')/range-to(id('tok_1215')))"/><!-- forsVdeesulVuncilVm'estdefensVCV -->
<mark id="line_80" xlink:href="#xpointer(id('tok_1216')/range-to(id('tok_1231')))"/><!-- coluiVCVneetucheraiVCeCVdeemainsV -->
<mark id="line_81" xlink:href="#xpointer(id('tok_1232')/range-to(id('tok_1247')))"/><!-- liVquelsVestcoVveezVVleetuVlaV -->
<mark id="line_82" xlink:href="#xpointer(id('tok_1248')/range-to(id('tok_1263')))"/><!-- coluiVCVtresVbienVmeedeviaVCVCV -->
<mark id="line_83" xlink:href="#xpointer(id('tok_1264')/range-to(id('tok_1279')))"/><!-- sezVtuVporVquoiVjoVcertesVCenonV -->
<mark id="line_84" xlink:href="#xpointer(id('tok_1280')/range-to(id('tok_1295')))"/><!-- joVteedirraiVCVjaVl'achaisonCVCV -->
<mark id="line_85" xlink:href="#xpointer(id('tok_1296')/range-to(id('tok_1311')))"/><!-- deel'altreCefruitVrienVneeliVchaltV -->
<mark id="line_86" xlink:href="#xpointer(id('tok_1312')/range-to(id('tok_1326')))"/><!-- forsVdeeceluiVCVquiVpentVenhaltV -->
<mark id="line_87" xlink:href="#xpointer(id('tok_1327')/range-to(id('tok_1342')))"/><!-- coVestleefruitVdeesapienceVCVVCe -->
<mark id="line_88" xlink:href="#xpointer(id('tok_1343')/range-to(id('tok_1360')))"/><!-- deetutVsaveirVCVdoneVCescienceVCVCe -->
<mark id="line_89" xlink:href="#xpointer(id('tok_1361')/range-to(id('tok_1377')))"/><!-- seetuVleemanjuesVCVebonVleefrasV -->
<mark id="line_90" xlink:href="#xpointer(id('tok_1378')/range-to(id('tok_1391')))"/><!-- ejoVenqueiVtuVleeverrasVCV -->
<mark id="line_91" xlink:href="#xpointer(id('tok_1392')/range-to(id('tok_1405')))"/><!-- tiVoilserruntVCVsempresVCeovertCV -->
<mark id="line_92" xlink:href="#xpointer(id('tok_1406')/range-to(id('tok_1419')))"/><!-- quanqueVCedeitVestreCetiertapertCV -->
<mark id="line_93" xlink:href="#xpointer(id('tok_1420')/range-to(id('tok_1435')))"/><!-- quanqueVCevuldrasVCVporrasVCVfaireVCe -->
<mark id="line_94" xlink:href="#xpointer(id('tok_1436')/range-to(id('tok_1452')))"/><!-- multVleefaitVbonVversVteiVatraireCVCe -->
<mark id="line_95" xlink:href="#xpointer(id('tok_1453')/range-to(id('tok_1465')))"/><!-- manjueVCVeleesiVfrasVbienV -->
<mark id="line_96" xlink:href="#xpointer(id('tok_1466')/range-to(id('tok_1481')))"/><!-- neecrendrasVCVpoisVtunVdeuVdeerienV -->
<mark id="line_97" xlink:href="#xpointer(id('tok_1482')/range-to(id('tok_1496')))"/><!-- aienzserrasVCVpuisVdelVtutVsonVperV -->
<mark id="line_98" xlink:href="#xpointer(id('tok_1497')/range-to(id('tok_1509')))"/><!-- porVcoVleequidatVCVveerVV -->
<mark id="line_99" xlink:href="#xpointer(id('tok_1510')/range-to(id('tok_1525')))"/><!-- creraseCVmeetuVgusteVCedelVfruitV -->
<mark id="line_100" xlink:href="#xpointer(id('tok_1526')/range-to(id('tok_1540')))"/><!-- noVelfraiVpasVoroezCVdeduitVCV -->
<mark id="line_101" xlink:href="#xpointer(id('tok_1541')/range-to(id('tok_1556')))"/><!-- neel'ferasVCVnonVkarVtuVessozV -->
<mark id="line_102" xlink:href="#xpointer(id('tok_1557')/range-to(id('tok_1573')))"/><!-- encoreCVCeteemembreraVCeCVdesVmozV -->
<mark id="line_103" xlink:href="#xpointer(id('tok_1574')/range-to(id('tok_1590')))"/><!-- adamCVqueefaisVchangerasVCeCVtunVsensV -->
<mark id="line_104" xlink:href="#xpointer(id('tok_1591')/range-to(id('tok_1605')))"/><!-- estuVencoreCVCeenfolVporpensVCV -->
<mark id="line_105" xlink:href="#xpointer(id('tok_1606')/range-to(id('tok_1622')))"/><!-- joVl'teequidaiVCVdireVCel'autrerCV -->
<mark id="line_106" xlink:href="#xpointer(id('tok_1623')/range-to(id('tok_1638')))"/><!-- deusVtafaitVciVsunVprovenderVCVCV -->
<mark id="line_107" xlink:href="#xpointer(id('tok_1639')/range-to(id('tok_1654')))"/><!-- ciVtadmisVporVmangierVCVcestVfruitV -->
<mark id="line_108" xlink:href="#xpointer(id('tok_1655')/range-to(id('tok_1666')))"/><!-- astuVdonchValtreCededuitVCV -->
<mark id="line_109" xlink:href="#xpointer(id('tok_1667')/range-to(id('tok_1676')))"/><!-- joVoïlVneemeefaltV -->
<mark id="line_110" xlink:href="#xpointer(id('tok_1677')/range-to(id('tok_1692')))"/><!-- neemunterasVCeCVjaVmesVplusVhaltV -->
<mark id="line_111" xlink:href="#xpointer(id('tok_1693')/range-to(id('tok_1708')))"/><!-- moltVteeporrasVCVtenirVCVporVchierV -->
<mark id="line_112" xlink:href="#xpointer(id('tok_1709')/range-to(id('tok_1724')))"/><!-- quantVdeusVtafetVsunVjardenierVCVCV -->
<mark id="line_113" xlink:href="#xpointer(id('tok_1725')/range-to(id('tok_1739')))"/><!-- deusVtafeitVgardeinVCVdeesonVort -->
<mark id="line_114" xlink:href="#xpointer(id('tok_1740')/range-to(id('tok_1754')))"/><!-- jaVneequerrasVCValtreCedeportVCV -->
<mark id="line_115" xlink:href="#xpointer(id('tok_1755')/range-to(id('tok_1771')))"/><!-- formaVCViltoiVporVventreVCefaireVCe -->
<mark id="line_116" xlink:href="#xpointer(id('tok_1772')/range-to(id('tok_1790')))"/><!-- altreCehonorCVneeteevoldraVCVatraireCVCe -->
<mark id="line_117" xlink:href="#xpointer(id('tok_1791')/range-to(id('tok_1802')))"/><!-- escutCVadamCVententCVamoiV -->
<mark id="line_118" xlink:href="#xpointer(id('tok_1803')/range-to(id('tok_1817')))"/><!-- joVteeconseilleraiVCVCeCVenfeiV -->
<mark id="line_119" xlink:href="#xpointer(id('tok_1818')/range-to(id('tok_1832')))"/><!-- queeporrasVCVestreCesenzVseignorVCV -->
<mark id="line_120" xlink:href="#xpointer(id('tok_1833')/range-to(id('tok_1847')))"/><!-- eserasVCVperVdelVcreaturVCVCV -->
<mark id="line_121" xlink:href="#xpointer(id('tok_1848')/range-to(id('tok_1865')))"/><!-- joVteedirraiVCVtuteVCelaVsummeVCe -->
<mark id="line_122" xlink:href="#xpointer(id('tok_1866')/range-to(id('tok_1880')))"/><!-- siVtuVmanjuesVCVelaVpomeVCe -->
<mark id="line_123" xlink:href="#xpointer(id('tok_1881')/range-to(id('tok_1895')))"/><!-- tuVregnerasVCeCVenmajestéVCVCV -->
<mark id="line_124" xlink:href="#xpointer(id('tok_1896')/range-to(id('tok_1911')))"/><!-- oddeuVpoezVCVpartirVCVpoestéVCVV -->
<mark id="line_125" xlink:href="#xpointer(id('tok_1912')/range-to(id('tok_1926')))"/><!-- fuiVteiVdeeciVqueeditVadamCV -->
<mark id="line_126" xlink:href="#xpointer(id('tok_1927')/range-to(id('tok_1941')))"/><!-- fuiVteiVdeeciVtuVessathanVCV -->
<mark id="line_127" xlink:href="#xpointer(id('tok_1942')/range-to(id('tok_1958')))"/><!-- malVconseilVCVdonesVCeejoVcomentVCV -->
<mark id="line_128" xlink:href="#xpointer(id('tok_1959')/range-to(id('tok_1973')))"/><!-- tuVmeevoelsVlivrerVCVatormentVCV -->
<mark id="line_129" xlink:href="#xpointer(id('tok_1974')/range-to(id('tok_1988')))"/><!-- meslerVCVmeevolsVomunVseignorVCV -->
<mark id="line_130" xlink:href="#xpointer(id('tok_1989')/range-to(id('tok_2006')))"/><!-- tolirVCVdeejoieVemettreVCeendolorVCV -->
<mark id="line_131" xlink:href="#xpointer(id('tok_2007')/range-to(id('tok_2022')))"/><!-- neeteecrerraiVCVfuiVteedeeciV -->
<mark id="line_132" xlink:href="#xpointer(id('tok_2023')/range-to(id('tok_2037')))"/><!-- neesoiesVejaVmaisVtantVhardiVCV -->
<mark id="line_133" xlink:href="#xpointer(id('tok_2038')/range-to(id('tok_2053')))"/><!-- queetuVjaVviengezVCVdevantVCVmoiV -->
<mark id="line_134" xlink:href="#xpointer(id('tok_2054')/range-to(id('tok_2067')))"/><!-- tuVestraitresVCVCeesanzVfoiV -->
<mark id="line_135" xlink:href="#xpointer(id('tok_2068')/range-to(id('tok_2081')))"/><!-- evaCecaVsuiVvenuzVCVatoiV -->
<mark id="line_136" xlink:href="#xpointer(id('tok_2082')/range-to(id('tok_2096')))"/><!-- diVmoiVsathanVCVettuVpurVquoiV -->
<mark id="line_137" xlink:href="#xpointer(id('tok_2097')/range-to(id('tok_2113')))"/><!-- joVvoisVquerantVCVtunVpruVtunVhonorCV -->
<mark id="line_138" xlink:href="#xpointer(id('tok_2114')/range-to(id('tok_2129')))"/><!-- coVdungeVCedeuVnaiezCVpoürVCV -->
<mark id="line_139" xlink:href="#xpointer(id('tok_2130')/range-to(id('tok_2144')))"/><!-- moltVagrantVtensVqueejoVaiaprisCV -->
<mark id="line_140" xlink:href="#xpointer(id('tok_2145')/range-to(id('tok_2160')))"/><!-- tozVlesVconseilsVCVdeeparaisVCVCV -->
<mark id="line_141" xlink:href="#xpointer(id('tok_2161')/range-to(id('tok_2174')))"/><!-- uneCepartieVCVetendirraiVCV -->
<mark id="line_142" xlink:href="#xpointer(id('tok_2175')/range-to(id('tok_2192')))"/><!-- oreCeleecomenceVCVCeejoVl'orraiCV -->
<mark id="line_143" xlink:href="#xpointer(id('tok_2193')/range-to(id('tok_2205')))"/><!-- orrasCVmeetuVsiVfraiVbienV -->
<mark id="line_144" xlink:href="#xpointer(id('tok_2206')/range-to(id('tok_2219')))"/><!-- neeteecurceraiVCeCVdeerienV -->
<mark id="line_145" xlink:href="#xpointer(id('tok_2220')/range-to(id('tok_2233')))"/><!-- celerasVCeCVm'enoïlVparVfoiV -->
<mark id="line_146" xlink:href="#xpointer(id('tok_2234')/range-to(id('tok_2248')))"/><!-- iertdescovertVCVCVnenilVCVparVmoiV -->
<mark id="line_147" xlink:href="#xpointer(id('tok_2249')/range-to(id('tok_2264')))"/><!-- ormeemetraiVCVentaVcreanceVCVCe -->
<mark id="line_148" xlink:href="#xpointer(id('tok_2265')/range-to(id('tok_2281')))"/><!-- neevoilVdeetoiValtreCefianceVCVCe -->
<mark id="line_149" xlink:href="#xpointer(id('tok_2282')/range-to(id('tok_2300')))"/><!-- bienVteepoisVcreireVCeamaVparoleVCVCe -->
<mark id="line_150" xlink:href="#xpointer(id('tok_2301')/range-to(id('tok_2316')))"/><!-- tuVasestéCVenboneVCeescoleCVCe -->
<mark id="line_151" xlink:href="#xpointer(id('tok_2317')/range-to(id('tok_2330')))"/><!-- joVviVadamCVmaisVtropVestfolsV -->
<mark id="line_152" xlink:href="#xpointer(id('tok_2331')/range-to(id('tok_2343')))"/><!-- unpoiVestdursVilserraVCVmolsV -->
<mark id="line_153" xlink:href="#xpointer(id('tok_2344')/range-to(id('tok_2356')))"/><!-- ilestplusVdorsVqueenestemfersCV -->
<mark id="line_154" xlink:href="#xpointer(id('tok_2357')/range-to(id('tok_2368')))"/><!-- ilestmultVfrancsVainzestmultVserfV -->
<mark id="line_155" xlink:href="#xpointer(id('tok_2369')/range-to(id('tok_2384')))"/><!-- cureVCenenVvoeltVprendreVCedeesoiV -->
<mark id="line_156" xlink:href="#xpointer(id('tok_2385')/range-to(id('tok_2400')))"/><!-- carVlaVprengeVCesevalsVCVdeetoiV -->
<mark id="line_157" xlink:href="#xpointer(id('tok_2401')/range-to(id('tok_2418')))"/><!-- tuVesfiebletteVCVCeettendreVCechoseVCe -->
<mark id="line_158" xlink:href="#xpointer(id('tok_2419')/range-to(id('tok_2434')))"/><!-- eesplusVfrescheVCequeenestroseVCe -->
<mark id="line_159" xlink:href="#xpointer(id('tok_2435')/range-to(id('tok_2449')))"/><!-- tuVesplusVblancheVCequeecristalVCV -->
<mark id="line_160" xlink:href="#xpointer(id('tok_2450')/range-to(id('tok_2466')))"/><!-- queeneifVqueechiétVsorVglaceVCeenvalCV -->
<mark id="line_161" xlink:href="#xpointer(id('tok_2467')/range-to(id('tok_2483')))"/><!-- malVcupleVCeemfistVliVcriatorVCVCV -->
<mark id="line_162" xlink:href="#xpointer(id('tok_2484')/range-to(id('tok_2498')))"/><!-- tuVestropVtendreVCeeiltropVdurV -->
<mark id="line_163" xlink:href="#xpointer(id('tok_2499')/range-to(id('tok_2515')))"/><!-- maisVneporquantVCVCVtuVesplusVsageVCe -->
<mark id="line_164" xlink:href="#xpointer(id('tok_2516')/range-to(id('tok_2531')))"/><!-- engrantVsensVasmisVtunVcorrageVCVCe -->
<mark id="line_165" xlink:href="#xpointer(id('tok_2532')/range-to(id('tok_2546')))"/><!-- porVcoVfaitVbonVtraireVCeatoiV -->
<mark id="line_166" xlink:href="#xpointer(id('tok_2547')/range-to(id('tok_2561')))"/><!-- parlerVCVteevoilVoreCeiaitfaiV -->
<mark id="line_167" xlink:href="#xpointer(id('tok_2562')/range-to(id('tok_2579')))"/><!-- nenVsacheVCenulsVkiVleedeitVsaverVCV -->
<mark id="line_168" xlink:href="#xpointer(id('tok_2580')/range-to(id('tok_2593')))"/><!-- neïsVVadamCVnenilVCVparVmoiV -->
<mark id="line_169" xlink:href="#xpointer(id('tok_2594')/range-to(id('tok_2609')))"/><!-- orteedirraiVCVetuVm'ascuteCVCe -->
<mark id="line_170" xlink:href="#xpointer(id('tok_2610')/range-to(id('tok_2626')))"/><!-- naqueenusVdousVencesteVCeroteVCe -->
<mark id="line_171" xlink:href="#xpointer(id('tok_2627')/range-to(id('tok_2639')))"/><!-- eadamCVlaVquilneenusVot -->
<mark id="line_172" xlink:href="#xpointer(id('tok_2640')/range-to(id('tok_2654')))"/><!-- parlezVCVenhaltVnensavratVCVmoltV -->
<mark id="line_173" xlink:href="#xpointer(id('tok_2655')/range-to(id('tok_2668')))"/><!-- joVvusVacointCVdungrantVenginCV -->
<mark id="line_174" xlink:href="#xpointer(id('tok_2669')/range-to(id('tok_2682')))"/><!-- queevusVestfaitVencestVgardinVCV -->
<mark id="line_175" xlink:href="#xpointer(id('tok_2683')/range-to(id('tok_2697')))"/><!-- leefruitVqueedeusVvusVaddonéVCV -->
<mark id="line_176" xlink:href="#xpointer(id('tok_2698')/range-to(id('tok_2711')))"/><!-- nenVaensoiVgairesVCebontéVCV -->
<mark id="line_177" xlink:href="#xpointer(id('tok_2712')/range-to(id('tok_2726')))"/><!-- cilVquilvusVadtantVdefenduVCVCV -->
<mark id="line_178" xlink:href="#xpointer(id('tok_2727')/range-to(id('tok_2737')))"/><!-- iladensoiVgrantVvertuVCV -->
<mark id="line_179" xlink:href="#xpointer(id('tok_2738')/range-to(id('tok_2752')))"/><!-- enceluiVCVestgraceVCedeevieVe -->
<mark id="line_180" xlink:href="#xpointer(id('tok_2753')/range-to(id('tok_2770')))"/><!-- deepoesteVCVCeedeeseignorieVCVCVe -->
<mark id="line_181" xlink:href="#xpointer(id('tok_2771')/range-to(id('tok_2783')))"/><!-- deetutVsaverVCVbienVemalV -->
<mark id="line_182" xlink:href="#xpointer(id('tok_2784')/range-to(id('tok_2798')))"/><!-- quelVsavorVCVacelestialVCVCVCV -->
<mark id="line_183" xlink:href="#xpointer(id('tok_2799')/range-to(id('tok_2814')))"/><!-- atonVbelsVcorsVataVfigureVCVCe -->
<mark id="line_184" xlink:href="#xpointer(id('tok_2815')/range-to(id('tok_2831')))"/><!-- bienVcovendreitVCVCVtelVaventureCVCVCe -->
<mark id="line_185" xlink:href="#xpointer(id('tok_2832')/range-to(id('tok_2847')))"/><!-- queetuVfussesVCedameVCedelVmondV -->
<mark id="line_186" xlink:href="#xpointer(id('tok_2848')/range-to(id('tok_2862')))"/><!-- delVsoverainVCeCVetdelVparfontVCV -->
<mark id="line_187" xlink:href="#xpointer(id('tok_2863')/range-to(id('tok_2876')))"/><!-- eseusezVVCVquanqueVCeaestreCe -->
<mark id="line_188" xlink:href="#xpointer(id('tok_2877')/range-to(id('tok_2894')))"/><!-- queedeetuitVfuissezVCVboneVCemaistreVCe -->
<mark id="line_189" xlink:href="#xpointer(id('tok_2895')/range-to(id('tok_2907')))"/><!-- esttelVliVfruizVoïlVparVvoirV -->
<mark id="line_190" xlink:href="#xpointer(id('tok_2908')/range-to(id('tok_2922')))"/><!-- jaVmeefaitVbienVsolVleeveerVV -->
<mark id="line_191" xlink:href="#xpointer(id('tok_2923')/range-to(id('tok_2938')))"/><!-- siVtuVleemanguesVCequeeferasVCV -->
<mark id="line_192" xlink:href="#xpointer(id('tok_2939')/range-to(id('tok_2953')))"/><!-- ejoVqueesaiVneemeecrerrasVCV -->
<mark id="line_193" xlink:href="#xpointer(id('tok_2954')/range-to(id('tok_2972')))"/><!-- primesVCeleepreneeaadamCVleedoneVCe -->
<mark id="line_194" xlink:href="#xpointer(id('tok_2973')/range-to(id('tok_2991')))"/><!-- delVcielVaverezCeCVsempresVCecoroneVCVCe -->
<mark id="line_195" xlink:href="#xpointer(id('tok_2992')/range-to(id('tok_3006')))"/><!-- alcreatorVCVCVserrezVCVpareilVCV -->
<mark id="line_196" xlink:href="#xpointer(id('tok_3007')/range-to(id('tok_3022')))"/><!-- neevusVpurraVCVcelerVCVconseilVCV -->
<mark id="line_197" xlink:href="#xpointer(id('tok_3023')/range-to(id('tok_3037')))"/><!-- puisqueVCedelVfruitVavrezCVmangiéVCV -->
<mark id="line_198" xlink:href="#xpointer(id('tok_3038')/range-to(id('tok_3052')))"/><!-- sempresVCevusViertleecuerVchangiéVCV -->
<mark id="line_199" xlink:href="#xpointer(id('tok_3053')/range-to(id('tok_3067')))"/><!-- odeusVserrezVCVsanzVfaillanceVCVCe -->
<mark id="line_200" xlink:href="#xpointer(id('tok_3068')/range-to(id('tok_3087')))"/><!-- deeegalCVbontéVCVdeeegalCVpuissanceVCVCe -->
<mark id="line_201" xlink:href="#xpointer(id('tok_3088')/range-to(id('tok_3103')))"/><!-- gusteVCedelVfruitVjoVnairegardVCV -->
<mark id="line_202" xlink:href="#xpointer(id('tok_3104')/range-to(id('tok_3119')))"/><!-- neecreireVCeadamCVjoVl'feraiVCV -->
<mark id="line_203" xlink:href="#xpointer(id('tok_3120')/range-to(id('tok_3127')))"/><!-- quantVsuffrezVCVmoiV -->
<mark id="line_204" xlink:href="#xpointer(id('tok_3128')/range-to(id('tok_3141')))"/><!-- tantVqueeadamCVsoitVenrecoiVCV -->
<mark id="line_205" xlink:href="#xpointer(id('tok_3142')/range-to(id('tok_3158')))"/><!-- manjueVCVeleenaiezCVdutanceVCVCe -->
<mark id="line_206" xlink:href="#xpointer(id('tok_3159')/range-to(id('tok_3175')))"/><!-- leedemorerVCVCVserratVCVemfanceCVCe -->
<mark id="line_207" xlink:href="#xpointer(id('tok_3176')/range-to(id('tok_3191')))"/><!-- diVmoiVmuillerVCVqueeteequerroitVCV -->
<mark id="line_208" xlink:href="#xpointer(id('tok_3192')/range-to(id('tok_3207')))"/><!-- liVmalVsatanVCVqueeteevoleitVCV -->
<mark id="line_209" xlink:href="#xpointer(id('tok_3208')/range-to(id('tok_3223')))"/><!-- ilmeeparlaVCVdeenostreVCehonorCV -->
<mark id="line_210" xlink:href="#xpointer(id('tok_3224')/range-to(id('tok_3239')))"/><!-- neecreireVCejaVleetraitorVCVCV -->
<mark id="line_211" xlink:href="#xpointer(id('tok_3240')/range-to(id('tok_3253')))"/><!-- ilesttraitreVCVCebienVleesaiV -->
<mark id="line_212" xlink:href="#xpointer(id('tok_3254')/range-to(id('tok_3268')))"/><!-- etuVcomentVCVcarVl'asaiaiCVCV -->
<mark id="line_213" xlink:href="#xpointer(id('tok_3269')/range-to(id('tok_3283')))"/><!-- deecoVquenchatVmeedelVveerVV -->
<mark id="line_214" xlink:href="#xpointer(id('tok_3284')/range-to(id('tok_3298')))"/><!-- ilteeferraVCVchangerVCVsaverVCV -->
<mark id="line_215" xlink:href="#xpointer(id('tok_3299')/range-to(id('tok_3314')))"/><!-- neel'fraVpasVcarVneel'creraiVCV -->
<mark id="line_216" xlink:href="#xpointer(id('tok_3315')/range-to(id('tok_3330')))"/><!-- deenuleVCerienVtantqueVCel'asaiCV -->
<mark id="line_217" xlink:href="#xpointer(id('tok_3331')/range-to(id('tok_3347')))"/><!-- neel'laisserVCVmaisVvenirVCVsorVtoiV -->
<mark id="line_218" xlink:href="#xpointer(id('tok_3348')/range-to(id('tok_3361')))"/><!-- carVilestmultVdeeputeVCefoiV -->
<mark id="line_219" xlink:href="#xpointer(id('tok_3362')/range-to(id('tok_3376')))"/><!-- ilvolstVtrairVCVjaVsonVseignorVCV -->
<mark id="line_220" xlink:href="#xpointer(id('tok_3377')/range-to(id('tok_3390')))"/><!-- esoposerCVCValdesVhalzorVCV -->
<mark id="line_221" xlink:href="#xpointer(id('tok_3391')/range-to(id('tok_3405')))"/><!-- telVpaltonierVCVCVquiVcoVadfaitV -->
<mark id="line_222" xlink:href="#xpointer(id('tok_3406')/range-to(id('tok_3422')))"/><!-- neevoilVqueeversVvusVaitnulVretraitVCV -->
<mark id="line_223" xlink:href="#xpointer(id('tok_3423')/range-to(id('tok_3437')))"/><!-- manjueVCVeadamCVneesezVqueeest -->
<mark id="line_224" xlink:href="#xpointer(id('tok_3438')/range-to(id('tok_3452')))"/><!-- pernumVCVcoVbienVqueenusVestprestV -->
<mark id="line_225" xlink:href="#xpointer(id('tok_3453')/range-to(id('tok_3468')))"/><!-- estiltantVbonVtuVleesaverasVCeCV -->
<mark id="line_226" xlink:href="#xpointer(id('tok_3469')/range-to(id('tok_3488')))"/><!-- neel'poezVCVsaverVCVsiVngusterasVCeCV -->
<mark id="line_227" xlink:href="#xpointer(id('tok_3489')/range-to(id('tok_3502')))"/><!-- jenduitVlaiVleenenVfraiVpasV -->
<mark id="line_228" xlink:href="#xpointer(id('tok_3503')/range-to(id('tok_3518')))"/><!-- delVdemorerVCVCVfaiVtuVqueelasV -->
<mark id="line_229" xlink:href="#xpointer(id('tok_3519')/range-to(id('tok_3534')))"/><!-- ejoVleeprendraiVCVmanjueVCVetene -->
<mark id="line_230" xlink:href="#xpointer(id('tok_3535')/range-to(id('tok_3550')))"/><!-- parVcoVsaverasVCeCVemalVebienV -->
<mark id="line_231" xlink:href="#xpointer(id('tok_3551')/range-to(id('tok_3567')))"/><!-- joVenmanjeraiVCeCVpremirementVCVCeCV -->
<mark id="line_232" xlink:href="#xpointer(id('tok_3568')/range-to(id('tok_3580')))"/><!-- ejoVaprésCVseurementVVCeCV -->
<mark id="line_233" xlink:href="#xpointer(id('tok_3581')/range-to(id('tok_3596')))"/><!-- gustéVCVenaideusVqueleVCesavorVCV -->
<mark id="line_234" xlink:href="#xpointer(id('tok_3597')/range-to(id('tok_3611')))"/><!-- uncneetastaiVCVditelCVdolcorVCV -->
<mark id="line_235" xlink:href="#xpointer(id('tok_3612')/range-to(id('tok_3628')))"/><!-- ditelCVsavorVCVestcesteVCepomeVCe -->
<mark id="line_236" xlink:href="#xpointer(id('tok_3629')/range-to(id('tok_3645')))"/><!-- deequelVditelCVnenVgustaVCVhomeCe -->
<mark id="line_237" xlink:href="#xpointer(id('tok_3646')/range-to(id('tok_3658')))"/><!-- orsuntVmesVoiltantVclerVveantVV -->
<mark id="line_238" xlink:href="#xpointer(id('tok_3659')/range-to(id('tok_3674')))"/><!-- joVsembleVCedeuVleetuitVpuissantVCV -->
<mark id="line_239" xlink:href="#xpointer(id('tok_3675')/range-to(id('tok_3689')))"/><!-- quanqueVCefuVquanqueVCedoitVestreCe -->
<mark id="line_240" xlink:href="#xpointer(id('tok_3690')/range-to(id('tok_3706')))"/><!-- saiVjoVtrestutVCVbienVensuiVmaistreVCe -->
<mark id="line_241" xlink:href="#xpointer(id('tok_3707')/range-to(id('tok_3724')))"/><!-- manjueVCVeadamCVneefazVdemoreVCVCe -->
<mark id="line_242" xlink:href="#xpointer(id('tok_3725')/range-to(id('tok_3740')))"/><!-- tuVleeprendrasVCVenmultVbonVoreCe -->
<mark id="line_243" xlink:href="#xpointer(id('tok_3741')/range-to(id('tok_3755')))"/><!-- joVtencrerraVCVtuVesmaVperV -->
<mark id="line_244" xlink:href="#xpointer(id('tok_3756')/range-to(id('tok_3770')))"/><!-- manjueVCVenenVpoezVCVdoterVCV -->
<mark id="line_245" xlink:href="#xpointer(id('tok_3771')/range-to(id('tok_3784')))"/><!-- allasCVpecchorVCVqueeaijoVfaitV -->
<mark id="line_246" xlink:href="#xpointer(id('tok_3785')/range-to(id('tok_3797')))"/><!-- orsuiVmortVsanzVnulVretraitVCV -->
<mark id="line_247" xlink:href="#xpointer(id('tok_3798')/range-to(id('tok_3811')))"/><!-- senzVnulVrescusVCVsuiVjoVmortV -->
<mark id="line_248" xlink:href="#xpointer(id('tok_3812')/range-to(id('tok_3824')))"/><!-- tantVestchaiteVCemalVmaVsortV -->
<mark id="line_249" xlink:href="#xpointer(id('tok_3825')/range-to(id('tok_3841')))"/><!-- malVm'estchangéVCVmaVaventureCVCVCe -->
<mark id="line_250" xlink:href="#xpointer(id('tok_3842')/range-to(id('tok_3859')))"/><!-- multVfuVjaVboneVCeorestmultVdoreVCe -->
<mark id="line_251" xlink:href="#xpointer(id('tok_3860')/range-to(id('tok_3874')))"/><!-- joVaiguerpiVCVmunVcriatorVCVCV -->
<mark id="line_252" xlink:href="#xpointer(id('tok_3875')/range-to(id('tok_3889')))"/><!-- parVleeconseilVCVdeemalVuxorCV -->
<mark id="line_253" xlink:href="#xpointer(id('tok_3890')/range-to(id('tok_3902')))"/><!-- allasCVpecchableVCVCequeefraiV -->
<mark id="line_254" xlink:href="#xpointer(id('tok_3903')/range-to(id('tok_3917')))"/><!-- munVcriatorVCVCVcumVatendraiCVCV -->
<mark id="line_255" xlink:href="#xpointer(id('tok_3918')/range-to(id('tok_3932')))"/><!-- cumVatendraiCVCVmonVcriatorVCVCV -->
<mark id="line_256" xlink:href="#xpointer(id('tok_3933')/range-to(id('tok_3949')))"/><!-- queejoVaiguerpiVCVporVmaVfolorVCV -->
<mark id="line_257" xlink:href="#xpointer(id('tok_3950')/range-to(id('tok_3964')))"/><!-- unchesCeneefisVtantVmalVmarchiéVCV -->
<mark id="line_258" xlink:href="#xpointer(id('tok_3965')/range-to(id('tok_3978')))"/><!-- orsaiVjoVjaVqueeestpecchiéVCV -->
<mark id="line_259" xlink:href="#xpointer(id('tok_3979')/range-to(id('tok_3995')))"/><!-- aimortVporVquoiVmeelaissesVCevivreVCe -->
<mark id="line_260" xlink:href="#xpointer(id('tok_3996')/range-to(id('tok_4015')))"/><!-- queenestliVmondeVCedeemoiVdelivreVCVCe -->
<mark id="line_261" xlink:href="#xpointer(id('tok_4016')/range-to(id('tok_4029')))"/><!-- porVquoiVfazVencombrerCVCValmondV -->
<mark id="line_262" xlink:href="#xpointer(id('tok_4030')/range-to(id('tok_4045')))"/><!-- demferCVm'estoetCVtempterVCVleefondV -->
<mark id="line_263" xlink:href="#xpointer(id('tok_4046')/range-to(id('tok_4061')))"/><!-- enemferCVserraVCVmaVdemureVCVCe -->
<mark id="line_264" xlink:href="#xpointer(id('tok_4062')/range-to(id('tok_4079')))"/><!-- tantqueVCeviengeVCequiVmeesucureVCVCe -->
<mark id="line_265" xlink:href="#xpointer(id('tok_4080')/range-to(id('tok_4093')))"/><!-- enemferCVsiVavraiCVmaVvieVe -->
<mark id="line_266" xlink:href="#xpointer(id('tok_4094')/range-to(id('tok_4108')))"/><!-- dontVmeevendraVCVilocCVaïeCVe -->
<mark id="line_267" xlink:href="#xpointer(id('tok_4109')/range-to(id('tok_4123')))"/><!-- dontVmeevendraVCViloecCVsocorsVCV -->
<mark id="line_268" xlink:href="#xpointer(id('tok_4124')/range-to(id('tok_4139')))"/><!-- kiVmeetraraVCVditésCVdolorsVCV -->
<mark id="line_269" xlink:href="#xpointer(id('tok_4140')/range-to(id('tok_4155')))"/><!-- porVqueiVversVmonVseignorVCVmesfisVCV -->
<mark id="line_270" xlink:href="#xpointer(id('tok_4156')/range-to(id('tok_4169')))"/><!-- neemeedeitVestreCenulVamisCV -->
<mark id="line_271" xlink:href="#xpointer(id('tok_4170')/range-to(id('tok_4184')))"/><!-- nonViertnulVqueegairesVCevailleVCe -->
<mark id="line_272" xlink:href="#xpointer(id('tok_4185')/range-to(id('tok_4202')))"/><!-- joVsuiVperduVCVsenzVnuleVCefailleVCe -->
<mark id="line_273" xlink:href="#xpointer(id('tok_4203')/range-to(id('tok_4218')))"/><!-- versVmonVseignorVCVsuiVsiVmesfaitVCV -->
<mark id="line_274" xlink:href="#xpointer(id('tok_4219')/range-to(id('tok_4234')))"/><!-- nenVpuisVcontreVCeluiVentrerCVemplaitV -->
<mark id="line_275" xlink:href="#xpointer(id('tok_4235')/range-to(id('tok_4246')))"/><!-- carVjoVaitortVeiladdroitV -->
<mark id="line_276" xlink:href="#xpointer(id('tok_4247')/range-to(id('tok_4257')))"/><!-- deuVtantVaciVmalVplaitV -->
<mark id="line_277" xlink:href="#xpointer(id('tok_4258')/range-to(id('tok_4275')))"/><!-- chiVavradCVmaisVdeemoiVmemorieVCVCVe -->
<mark id="line_278" xlink:href="#xpointer(id('tok_4276')/range-to(id('tok_4292')))"/><!-- carVsuiVmesfetVCVauroiVdeegloireVCe -->
<mark id="line_279" xlink:href="#xpointer(id('tok_4293')/range-to(id('tok_4307')))"/><!-- auroiVdelVcielVsuiVsiVmesfaitVCV -->
<mark id="line_280" xlink:href="#xpointer(id('tok_4308')/range-to(id('tok_4322')))"/><!-- deeraisonVCVnaiversVluiVuntraitV -->
<mark id="line_281" xlink:href="#xpointer(id('tok_4323')/range-to(id('tok_4336')))"/><!-- nenVaiamiCVneenulVveisinVCV -->
<mark id="line_282" xlink:href="#xpointer(id('tok_4337')/range-to(id('tok_4349')))"/><!-- quiVmeetraiVdelVplaitVafinV -->
<mark id="line_283" xlink:href="#xpointer(id('tok_4350')/range-to(id('tok_4365')))"/><!-- quiVpreiraiVCVjoVjaVquiVm'aïtCV -->
<mark id="line_284" xlink:href="#xpointer(id('tok_4366')/range-to(id('tok_4379')))"/><!-- quantVmaVfemmeVCem'atraïtVCV -->
<mark id="line_285" xlink:href="#xpointer(id('tok_4380')/range-to(id('tok_4395')))"/><!-- quiVdeusVmeedonaVCVporVpareilVCV -->
<mark id="line_286" xlink:href="#xpointer(id('tok_4396')/range-to(id('tok_4410')))"/><!-- eleCemeedonaVCVmalVconseilVCV -->
<mark id="line_287" xlink:href="#xpointer(id('tok_4411')/range-to(id('tok_4425')))"/><!-- aieveCeaifemmeVCedeaveeVVCVe -->
<mark id="line_288" xlink:href="#xpointer(id('tok_4426')/range-to(id('tok_4440')))"/><!-- malVfussezVCVvusVdeemoiVneeVe -->
<mark id="line_289" xlink:href="#xpointer(id('tok_4441')/range-to(id('tok_4456')))"/><!-- carVfustVarseCeicesteCVCecosteVCe -->
<mark id="line_290" xlink:href="#xpointer(id('tok_4457')/range-to(id('tok_4473')))"/><!-- quiVm'admisVensiVmaleVCeposteVCe -->
<mark id="line_291" xlink:href="#xpointer(id('tok_4474')/range-to(id('tok_4491')))"/><!-- carVfustVlaVcosteVCeenfuVbrudleeVCVe -->
<mark id="line_292" xlink:href="#xpointer(id('tok_4492')/range-to(id('tok_4508')))"/><!-- quiVm'adbastiVCVsiVgrantVmesleeVCVe -->
<mark id="line_293" xlink:href="#xpointer(id('tok_4509')/range-to(id('tok_4524')))"/><!-- quantVceleVCecosteVCedeemoiVpristV -->
<mark id="line_294" xlink:href="#xpointer(id('tok_4525')/range-to(id('tok_4538')))"/><!-- porVqueiVneel'arstemoiVoscistCV -->
<mark id="line_295" xlink:href="#xpointer(id('tok_4539')/range-to(id('tok_4553')))"/><!-- laVcosteVCeadtutVleecorsVtraiV -->
<mark id="line_296" xlink:href="#xpointer(id('tok_4554')/range-to(id('tok_4566')))"/><!-- eafoléCVCVemalVbailliVCV -->
<mark id="line_297" xlink:href="#xpointer(id('tok_4567')/range-to(id('tok_4583')))"/><!-- neesaVqueedieVeneekenVfaceVCe -->
<mark id="line_298" xlink:href="#xpointer(id('tok_4584')/range-to(id('tok_4601')))"/><!-- siVneemeevientVdelVcielVlaVgraceVCe -->
<mark id="line_299" xlink:href="#xpointer(id('tok_4602')/range-to(id('tok_4618')))"/><!-- nemVpuisVestreCegietéVCVdeepaineVCe -->
<mark id="line_300" xlink:href="#xpointer(id('tok_4619')/range-to(id('tok_4635')))"/><!-- telVestliVmalsVqueemeedemaineVCVCe -->
<mark id="line_301" xlink:href="#xpointer(id('tok_4636')/range-to(id('tok_4647')))"/><!-- aieveCecumVamalVoreCe -->
<mark id="line_302" xlink:href="#xpointer(id('tok_4648')/range-to(id('tok_4667')))"/><!-- cumeVCegrantVpeineVCemeecurutVCVsoreVCe -->
<mark id="line_303" xlink:href="#xpointer(id('tok_4668')/range-to(id('tok_4682')))"/><!-- quantVonchesCefustesVCemiVparailVCV -->
<mark id="line_304" xlink:href="#xpointer(id('tok_4683')/range-to(id('tok_4699')))"/><!-- oreCesuiVperrizVCVparVtonVconseilVCV -->
<mark id="line_305" xlink:href="#xpointer(id('tok_4700')/range-to(id('tok_4714')))"/><!-- parVtonVconseilVCVsuiVmisVamalV -->
<mark id="line_306" xlink:href="#xpointer(id('tok_4715')/range-to(id('tok_4731')))"/><!-- deegrantVhaltesceVCVCesuiVmisVavalCV -->
<mark id="line_307" xlink:href="#xpointer(id('tok_4732')/range-to(id('tok_4746')))"/><!-- nenserraiVCVtraitVporVhomeCenéV -->
<mark id="line_308" xlink:href="#xpointer(id('tok_4747')/range-to(id('tok_4761')))"/><!-- siVdeuVnenVestdeemajestéVCVCV -->
<mark id="line_309" xlink:href="#xpointer(id('tok_4762')/range-to(id('tok_4779')))"/><!-- queediVjoVlasVporVquoiVleenomaiVCV -->
<mark id="line_310" xlink:href="#xpointer(id('tok_4780')/range-to(id('tok_4795')))"/><!-- ilmeeaideraCeCVcorocéVCVCVl'ai -->
<mark id="line_311" xlink:href="#xpointer(id('tok_4796')/range-to(id('tok_4811')))"/><!-- neemeeferatVCVjaVnulVaïeCVe -->
<mark id="line_312" xlink:href="#xpointer(id('tok_4812')/range-to(id('tok_4829')))"/><!-- forVleefilzVqueeistraCVdeemarieVCVe -->
<mark id="line_313" xlink:href="#xpointer(id('tok_4830')/range-to(id('tok_4845')))"/><!-- neesaiVdeenusVprendreVCeconroiVCV -->
<mark id="line_314" xlink:href="#xpointer(id('tok_4846')/range-to(id('tok_4860')))"/><!-- quantVadeuVneeportamesVCVCefoiV -->
<mark id="line_315" xlink:href="#xpointer(id('tok_4861')/range-to(id('tok_4873')))"/><!-- orensoitVtotVadeuVplaisirVCV -->
<mark id="line_316" xlink:href="#xpointer(id('tok_4874')/range-to(id('tok_4888')))"/><!-- niadconseilVCVqueedelVmorirVCV -->
<mark id="line_317" xlink:href="#xpointer(id('tok_4889')/range-to(id('tok_4900')))"/><!-- ciVsuiVjoVbealVsireVCe -->
<mark id="line_318" xlink:href="#xpointer(id('tok_4901')/range-to(id('tok_4917')))"/><!-- repostVCVmeesuiVjaVporVtaVireCe -->
<mark id="line_319" xlink:href="#xpointer(id('tok_4918')/range-to(id('tok_4930')))"/><!-- eporVcoVqueesuiVtutVnuzV -->
<mark id="line_320" xlink:href="#xpointer(id('tok_4931')/range-to(id('tok_4946')))"/><!-- meesuiVjeeiciCVsiVembatuzCVCV -->
<mark id="line_321" xlink:href="#xpointer(id('tok_4947')/range-to(id('tok_4959')))"/><!-- keeastuVfetVcumVaserréCV -->
<mark id="line_322" xlink:href="#xpointer(id('tok_4960')/range-to(id('tok_4975')))"/><!-- quiVtatoleitVCVdeetaVbontéVCV -->
<mark id="line_323" xlink:href="#xpointer(id('tok_4976')/range-to(id('tok_4991')))"/><!-- queeastuVfetVporVqueiVashonteVCe -->
<mark id="line_324" xlink:href="#xpointer(id('tok_4992')/range-to(id('tok_5006')))"/><!-- cumVentreraiCeCVodtoiVenconteVCe -->
<mark id="line_325" xlink:href="#xpointer(id('tok_5007')/range-to(id('tok_5018')))"/><!-- tuVnavoisCVrienVl'autrierCV -->
<mark id="line_326" xlink:href="#xpointer(id('tok_5019')/range-to(id('tok_5032')))"/><!-- duntVtuVdusesVCevergunderVCVCV -->
<mark id="line_327" xlink:href="#xpointer(id('tok_5033')/range-to(id('tok_5048')))"/><!-- orteevoiVmultVtristeVCeetmorneVCe -->
<mark id="line_328" xlink:href="#xpointer(id('tok_5049')/range-to(id('tok_5067')))"/><!-- malVsenVjoistVCVquiVensiCVsojorneVCVCe -->
<mark id="line_329" xlink:href="#xpointer(id('tok_5068')/range-to(id('tok_5086')))"/><!-- telVvergoineVCVCeaijoVsireVCedeetoiV -->
<mark id="line_330" xlink:href="#xpointer(id('tok_5087')/range-to(id('tok_5093')))"/><!-- etuVporVquoiV -->
<mark id="line_331" xlink:href="#xpointer(id('tok_5094')/range-to(id('tok_5110')))"/><!-- siVgrantVhonteVCemonVcorsVenlaceCVCe -->
<mark id="line_332" xlink:href="#xpointer(id('tok_5111')/range-to(id('tok_5124')))"/><!-- neetosveerVVenlaVfaceVCe -->
<mark id="line_333" xlink:href="#xpointer(id('tok_5125')/range-to(id('tok_5140')))"/><!-- porVqueiVtrespassasVCVCVmonVdevéVCV -->
<mark id="line_334" xlink:href="#xpointer(id('tok_5141')/range-to(id('tok_5152')))"/><!-- astuVgairesVCegaainniéVVCV -->
<mark id="line_335" xlink:href="#xpointer(id('tok_5153')/range-to(id('tok_5168')))"/><!-- tuVesmonVserfVejoVtonVsireVCe -->
<mark id="line_336" xlink:href="#xpointer(id('tok_5169')/range-to(id('tok_5185')))"/><!-- neel'teepuisVpasVcontredireVCeCVCe -->
<mark id="line_337" xlink:href="#xpointer(id('tok_5186')/range-to(id('tok_5200')))"/><!-- joVteeformaiVCVamonVsemblantVCV -->
<mark id="line_338" xlink:href="#xpointer(id('tok_5201')/range-to(id('tok_5216')))"/><!-- porVqueiVtrespassasVCVCVmonVcomantVCV -->
<mark id="line_339" xlink:href="#xpointer(id('tok_5217')/range-to(id('tok_5234')))"/><!-- joVtoiVplasmaiVCVdreitVamaVymageCVCe -->
<mark id="line_340" xlink:href="#xpointer(id('tok_5235')/range-to(id('tok_5249')))"/><!-- porVcoVmeefisVcelVoltrageCVCe -->
<mark id="line_341" xlink:href="#xpointer(id('tok_5250')/range-to(id('tok_5264')))"/><!-- munVdefensVCVunpasVneegardasVCV -->
<mark id="line_342" xlink:href="#xpointer(id('tok_5265')/range-to(id('tok_5280')))"/><!-- delivrementVCVCeCVleetrespassasVCVCV -->
<mark id="line_343" xlink:href="#xpointer(id('tok_5281')/range-to(id('tok_5296')))"/><!-- leefruitVmanjasVCVduntVjoVtoiditV -->
<mark id="line_344" xlink:href="#xpointer(id('tok_5297')/range-to(id('tok_5311')))"/><!-- queejoVtavoieCVecontreditVCeCV -->
<mark id="line_345" xlink:href="#xpointer(id('tok_5312')/range-to(id('tok_5326')))"/><!-- porVcoVquidasVCVestreCemonVperV -->
<mark id="line_346" xlink:href="#xpointer(id('tok_5327')/range-to(id('tok_5342')))"/><!-- neesaiVsiVtuVvoldrasVCVgabberVCV -->
<mark id="line_347" xlink:href="#xpointer(id('tok_5343')/range-to(id('tok_5358')))"/><!-- laVfemmeVCequeetuVmeedonasVCV -->
<mark id="line_348" xlink:href="#xpointer(id('tok_5359')/range-to(id('tok_5374')))"/><!-- eleCefistVprimeVCeicestCVtrespasVCV -->
<mark id="line_349" xlink:href="#xpointer(id('tok_5375')/range-to(id('tok_5389')))"/><!-- donatVCVleemoiVejoVmangaiVCV -->
<mark id="line_350" xlink:href="#xpointer(id('tok_5390')/range-to(id('tok_5405')))"/><!-- orm'estavisCVqueetornezVCVestagwaiV -->
<mark id="line_351" xlink:href="#xpointer(id('tok_5406')/range-to(id('tok_5419')))"/><!-- malVacontaiCVCVicestCVmangierVCV -->
<mark id="line_352" xlink:href="#xpointer(id('tok_5420')/range-to(id('tok_5434')))"/><!-- joVaimesfaitVCVparVmaVmoillerVCV -->
<mark id="line_353" xlink:href="#xpointer(id('tok_5435')/range-to(id('tok_5451')))"/><!-- taVmoillerVCVcreistesVVCeplusVqueemoiV -->
<mark id="line_354" xlink:href="#xpointer(id('tok_5452')/range-to(id('tok_5466')))"/><!-- manjasVCVleefruitVsanzVmonVotroiCV -->
<mark id="line_355" xlink:href="#xpointer(id('tok_5467')/range-to(id('tok_5480')))"/><!-- orteerendraiVCVitelCVguerdonVCV -->
<mark id="line_356" xlink:href="#xpointer(id('tok_5481')/range-to(id('tok_5495')))"/><!-- laVterreVCeavratCVmaleiconVCVCV -->
<mark id="line_357" xlink:href="#xpointer(id('tok_5496')/range-to(id('tok_5510')))"/><!-- outuVvoldrasVCVtonVbléVsemerVCV -->
<mark id="line_358" xlink:href="#xpointer(id('tok_5511')/range-to(id('tok_5524')))"/><!-- ilteefaldratVCValfruitVporterVCV -->
<mark id="line_359" xlink:href="#xpointer(id('tok_5525')/range-to(id('tok_5540')))"/><!-- eleCeestmaleiteVCVCesozVtaVmainV -->
<mark id="line_360" xlink:href="#xpointer(id('tok_5541')/range-to(id('tok_5555')))"/><!-- tuVleecotiverasVCVCeCVenvainV -->
<mark id="line_361" xlink:href="#xpointer(id('tok_5556')/range-to(id('tok_5569')))"/><!-- sonVfruitVatoiVdeveeratVCVVCV -->
<mark id="line_362" xlink:href="#xpointer(id('tok_5570')/range-to(id('tok_5585')))"/><!-- espinesCVCeechardonsVCVteerendratVCV -->
<mark id="line_363" xlink:href="#xpointer(id('tok_5586')/range-to(id('tok_5603')))"/><!-- changerVCVteevoldraVCVtaVsemenceVCVCe -->
<mark id="line_364" xlink:href="#xpointer(id('tok_5604')/range-to(id('tok_5618')))"/><!-- malaitVCViertporVtaVsentenceVCVCe -->
<mark id="line_365" xlink:href="#xpointer(id('tok_5619')/range-to(id('tok_5632')))"/><!-- odgrantVtravailVCVodgrantVhahanVCV -->
<mark id="line_366" xlink:href="#xpointer(id('tok_5633')/range-to(id('tok_5648')))"/><!-- toiVcovendraVCVCVmangerVCVtonVpanV -->
<mark id="line_367" xlink:href="#xpointer(id('tok_5649')/range-to(id('tok_5660')))"/><!-- odgrantVpaineVCeodgrantVsuorV -->
<mark id="line_368" xlink:href="#xpointer(id('tok_5661')/range-to(id('tok_5671')))"/><!-- vivrasVCVtuVnoitVejorV -->
<mark id="line_369" xlink:href="#xpointer(id('tok_5672')/range-to(id('tok_5685')))"/><!-- ettuVeveCemalaVCVmuillerVCV -->
<mark id="line_370" xlink:href="#xpointer(id('tok_5686')/range-to(id('tok_5702')))"/><!-- tostVmeecomencasVCVCVdeeguerreerVCVV -->
<mark id="line_371" xlink:href="#xpointer(id('tok_5703')/range-to(id('tok_5718')))"/><!-- poiVtenisVCVmesVcomandemenzVCVCeCV -->
<mark id="line_372" xlink:href="#xpointer(id('tok_5719')/range-to(id('tok_5734')))"/><!-- jaVm'engingnaCVCVliVmalVserpenzVCV -->
<mark id="line_373" xlink:href="#xpointer(id('tok_5735')/range-to(id('tok_5749')))"/><!-- parVluiVquidasVCVestreCemonVperV -->
<mark id="line_374" xlink:href="#xpointer(id('tok_5750')/range-to(id('tok_5763')))"/><!-- sesVtuVjaVbienVdevinerVCVCV -->
<mark id="line_375" xlink:href="#xpointer(id('tok_5764')/range-to(id('tok_5777')))"/><!-- oreinzCVaviezCVVlaVmaistrieVCVe -->
<mark id="line_376" xlink:href="#xpointer(id('tok_5778')/range-to(id('tok_5792')))"/><!-- deequanqueVCedoitVestreCeenvieVe -->
<mark id="line_377" xlink:href="#xpointer(id('tok_5793')/range-to(id('tok_5809')))"/><!-- cumVl'astuVjaVsiVtostVperdueVCVe -->
<mark id="line_378" xlink:href="#xpointer(id('tok_5810')/range-to(id('tok_5826')))"/><!-- orteevoiVtristeVCeetmalVvenueVCVe -->
<mark id="line_379" xlink:href="#xpointer(id('tok_5827')/range-to(id('tok_5838')))"/><!-- astuVfaitVgainVouperteVCe -->
<mark id="line_380" xlink:href="#xpointer(id('tok_5839')/range-to(id('tok_5854')))"/><!-- joVtoiVrendraiVCVtaVdeserteVCVCe -->
<mark id="line_381" xlink:href="#xpointer(id('tok_5855')/range-to(id('tok_5872')))"/><!-- joVtendonraiVCVporVtonVserviseVCVCe -->
<mark id="line_382" xlink:href="#xpointer(id('tok_5873')/range-to(id('tok_5889')))"/><!-- malVteevendraVCVentoteVCeguiseVCe -->
<mark id="line_383" xlink:href="#xpointer(id('tok_5890')/range-to(id('tok_5903')))"/><!-- endolorVCVporterasVCeCVemfanzCV -->
<mark id="line_384" xlink:href="#xpointer(id('tok_5904')/range-to(id('tok_5918')))"/><!-- eempaineVCevivrontVCVtotVlorVanz -->
<mark id="line_385" xlink:href="#xpointer(id('tok_5919')/range-to(id('tok_5932')))"/><!-- tesVemfanzCVendolorVCVnaistrontVCV -->
<mark id="line_386" xlink:href="#xpointer(id('tok_5933')/range-to(id('tok_5947')))"/><!-- eengrantVanguisseCVCefineruntVCeCV -->
<mark id="line_387" xlink:href="#xpointer(id('tok_5948')/range-to(id('tok_5963')))"/><!-- entelVhahanVCVentelVdamageVCVCe -->
<mark id="line_388" xlink:href="#xpointer(id('tok_5964')/range-to(id('tok_5977')))"/><!-- asmisVtoiVetunVlignageVCVCe -->
<mark id="line_389" xlink:href="#xpointer(id('tok_5978')/range-to(id('tok_5990')))"/><!-- toitVcealsVquiVdeetoiVistrontCV -->
<mark id="line_390" xlink:href="#xpointer(id('tok_5991')/range-to(id('tok_6004')))"/><!-- liVtonVpecchéVCVplorerontVCeCV -->
<mark id="line_391" xlink:href="#xpointer(id('tok_6005')/range-to(id('tok_6024')))"/><!-- goVsuiVmesfaitVCVcoVfuVparVfolageVCVCe -->
<mark id="line_392" xlink:href="#xpointer(id('tok_6025')/range-to(id('tok_6049')))"/><!-- porVuneCepomeVCesoffriraiVCVCVsiVgrantVdamageVCVCe -->
<mark id="line_393" xlink:href="#xpointer(id('tok_6050')/range-to(id('tok_6069')))"/><!-- queeenpaineVCemetVmoiVemonVlignageVCVCe -->
<mark id="line_394" xlink:href="#xpointer(id('tok_6070')/range-to(id('tok_6088')))"/><!-- petitVCVaquestCVmeerentVgrantVtrauageVCVCe -->
<mark id="line_395" xlink:href="#xpointer(id('tok_6089')/range-to(id('tok_6108')))"/><!-- siVjoVmesfisVCVneefuVmerveilleVCVCegrantV -->
<mark id="line_396" xlink:href="#xpointer(id('tok_6109')/range-to(id('tok_6126')))"/><!-- quantVtraiVmoiVleeserpentVCVsuduiantVCVCV -->
<mark id="line_397" xlink:href="#xpointer(id('tok_6127')/range-to(id('tok_6145')))"/><!-- multVsetVdeemalVnenVsembleVCepasVoeilleCe -->
<mark id="line_398" xlink:href="#xpointer(id('tok_6146')/range-to(id('tok_6165')))"/><!-- malVestbaillizVCVquiValuiVseeconseilleVCVCe -->
<mark id="line_399" xlink:href="#xpointer(id('tok_6166')/range-to(id('tok_6185')))"/><!-- laVpomeVCeprisVorsaiVqueefisVfolieVCVe -->
<mark id="line_400" xlink:href="#xpointer(id('tok_6186')/range-to(id('tok_6206')))"/><!-- sorVtonVdefensVCVdeecoVfisVfolonieVCVCVe -->
<mark id="line_401" xlink:href="#xpointer(id('tok_6207')/range-to(id('tok_6225')))"/><!-- malVengustaiVCVorsuiVdeetoiVhaïeVCVe -->
<mark id="line_402" xlink:href="#xpointer(id('tok_6226')/range-to(id('tok_6248')))"/><!-- porVpoiVdeefroitVmoiVcovientVCVperdreVCelaVvieVe -->
<mark id="line_403" xlink:href="#xpointer(id('tok_6249')/range-to(id('tok_6263')))"/><!-- etuVserpentVCVsoiezVCVmaleitVCV -->
<mark id="line_404" xlink:href="#xpointer(id('tok_6264')/range-to(id('tok_6279')))"/><!-- deetoiVreprendraiVCVCVbienVmonVdroitV -->
<mark id="line_405" xlink:href="#xpointer(id('tok_6280')/range-to(id('tok_6293')))"/><!-- sorVtonVpizVteetrainerasVCeCV -->
<mark id="line_406" xlink:href="#xpointer(id('tok_6294')/range-to(id('tok_6310')))"/><!-- atuzVlesVjorsVqueejaVviverasVCeCV -->
<mark id="line_407" xlink:href="#xpointer(id('tok_6311')/range-to(id('tok_6329')))"/><!-- laVpuldreVCeierttutVdisVtaVviandeVCVCe -->
<mark id="line_408" xlink:href="#xpointer(id('tok_6330')/range-to(id('tok_6340')))"/><!-- enboisVenplainVenlandeVCe -->
<mark id="line_409" xlink:href="#xpointer(id('tok_6341')/range-to(id('tok_6357')))"/><!-- femmeVCeteeporteraVCeCVhaineVVCe -->
<mark id="line_410" xlink:href="#xpointer(id('tok_6358')/range-to(id('tok_6375')))"/><!-- oncoreCVCeteeiertmaleVCeveisineVCVCe -->
<mark id="line_411" xlink:href="#xpointer(id('tok_6376')/range-to(id('tok_6390')))"/><!-- tuVsonVtalonVCVaguaiterasCVCeCV -->
<mark id="line_412" xlink:href="#xpointer(id('tok_6391')/range-to(id('tok_6406')))"/><!-- celeVCeteesacheraVCeCVleerasV -->
<mark id="line_413" xlink:href="#xpointer(id('tok_6407')/range-to(id('tok_6423')))"/><!-- taVtesteVCeferraVCVdeeitelCVmailV -->
<mark id="line_414" xlink:href="#xpointer(id('tok_6424')/range-to(id('tok_6439')))"/><!-- quiVteeferraVCVmultVgrantVtravailVCV -->
<mark id="line_415" xlink:href="#xpointer(id('tok_6440')/range-to(id('tok_6456')))"/><!-- encoreCVCeenprendraVCVbienVconreiVCVV -->
<mark id="line_416" xlink:href="#xpointer(id('tok_6457')/range-to(id('tok_6470')))"/><!-- cumVporraVCVvengierVCVdeetoiV -->
<mark id="line_417" xlink:href="#xpointer(id('tok_6471')/range-to(id('tok_6483')))"/><!-- malVacointasCVCVtuVsunVtrainV -->
<mark id="line_418" xlink:href="#xpointer(id('tok_6484')/range-to(id('tok_6497')))"/><!-- eleCeteefraVleechiefVenclinCV -->
<mark id="line_419" xlink:href="#xpointer(id('tok_6498')/range-to(id('tok_6511')))"/><!-- oncoreCVCeraizVdeeluiVistraCV -->
<mark id="line_420" xlink:href="#xpointer(id('tok_6512')/range-to(id('tok_6527')))"/><!-- quiVtozVtesVvertuzVCVconfundraVCVCV -->
<mark id="line_421" xlink:href="#xpointer(id('tok_6528')/range-to(id('tok_6543')))"/><!-- oreCeisséCVhorsVdeeparadisVCVCV -->
<mark id="line_422" xlink:href="#xpointer(id('tok_6544')/range-to(id('tok_6560')))"/><!-- malVchangeVCeavezCVfetVdeepaïsVCV -->
<mark id="line_423" xlink:href="#xpointer(id('tok_6561')/range-to(id('tok_6573')))"/><!-- enterreVCevusVfrezVmaisonVCV -->
<mark id="line_424" xlink:href="#xpointer(id('tok_6574')/range-to(id('tok_6588')))"/><!-- enparadisVCVCVnavezCVraisonVCV -->
<mark id="line_425" xlink:href="#xpointer(id('tok_6589')/range-to(id('tok_6603')))"/><!-- niavezCVrienVqueechalengierVCVCV -->
<mark id="line_426" xlink:href="#xpointer(id('tok_6604')/range-to(id('tok_6620')))"/><!-- forsVisterezCeCVsenVrecovererVCVCeCV -->
<mark id="line_427" xlink:href="#xpointer(id('tok_6621')/range-to(id('tok_6635')))"/><!-- niavezCVrienVparVjugementVCeCV -->
<mark id="line_428" xlink:href="#xpointer(id('tok_6636')/range-to(id('tok_6649')))"/><!-- orpernezVCVaillorsCVchasementVCeCV -->
<mark id="line_429" xlink:href="#xpointer(id('tok_6650')/range-to(id('tok_6663')))"/><!-- forsVenissezCVdeebonaurtéVCVCV -->
<mark id="line_430" xlink:href="#xpointer(id('tok_6664')/range-to(id('tok_6681')))"/><!-- neevusVfaltVmaisVfaimVneelassetéVCeCV -->
<mark id="line_431" xlink:href="#xpointer(id('tok_6682')/range-to(id('tok_6699')))"/><!-- neevusVfaltVmaisVdolorVCVneepaineVCe -->
<mark id="line_432" xlink:href="#xpointer(id('tok_6700')/range-to(id('tok_6716')))"/><!-- atozVlesVjorsVdeelaVsemaineVCVCe -->
<mark id="line_433" xlink:href="#xpointer(id('tok_6717')/range-to(id('tok_6732')))"/><!-- enterreVCeavrezCVmalvaisVCVsojorVCV -->
<mark id="line_434" xlink:href="#xpointer(id('tok_6733')/range-to(id('tok_6746')))"/><!-- aprésCVmorrezVCValchiefVdeetorV -->
<mark id="line_435" xlink:href="#xpointer(id('tok_6747')/range-to(id('tok_6762')))"/><!-- desVpoisVquaverezCeCVgustéVCVmortV -->
<mark id="line_436" xlink:href="#xpointer(id('tok_6763')/range-to(id('tok_6775')))"/><!-- enemferCVirrezCVsanzVdeportVCV -->
<mark id="line_437" xlink:href="#xpointer(id('tok_6776')/range-to(id('tok_6788')))"/><!-- iciCVavrontCVlesVcorsVeissilCV -->
<mark id="line_438" xlink:href="#xpointer(id('tok_6789')/range-to(id('tok_6801')))"/><!-- lesValmesCeenemfernCVperileCV -->
<mark id="line_439" xlink:href="#xpointer(id('tok_6802')/range-to(id('tok_6816')))"/><!-- satanVCVvusVavraCVenbaillieVCVe -->
<mark id="line_440" xlink:href="#xpointer(id('tok_6817')/range-to(id('tok_6832')))"/><!-- nesthomqueevusVenfaceVCeaïeCVe -->
<mark id="line_441" xlink:href="#xpointer(id('tok_6833')/range-to(id('tok_6848')))"/><!-- parVcuiVsoiezVCVvusVjaVrescosVCV -->
<mark id="line_442" xlink:href="#xpointer(id('tok_6849')/range-to(id('tok_6866')))"/><!-- seemoiVnenprengeVCepitéVCVdeevusV -->
<mark id="line_443" xlink:href="#xpointer(id('tok_6867')/range-to(id('tok_6882')))"/><!-- gardezVCVmoiVbienVleeparadisVCVCV -->
<mark id="line_444" xlink:href="#xpointer(id('tok_6883')/range-to(id('tok_6898')))"/><!-- queemaisVnientreCeicistCVfaudisVCV -->
<mark id="line_445" xlink:href="#xpointer(id('tok_6899')/range-to(id('tok_6915')))"/><!-- quilnaitmaisVpoeirVCVneebaillieVCVe -->
<mark id="line_446" xlink:href="#xpointer(id('tok_6916')/range-to(id('tok_6932')))"/><!-- needeetocherVCVliVfruitVdeevieVe -->
<mark id="line_447" xlink:href="#xpointer(id('tok_6933')/range-to(id('tok_6947')))"/><!-- oceleVCespeeVequiVflamboieVCVe -->
<mark id="line_448" xlink:href="#xpointer(id('tok_6948')/range-to(id('tok_6966')))"/><!-- siVliVdefendezVCVCVtresVbienVlaVvoieVe -->
<mark id="line_449" xlink:href="#xpointer(id('tok_6967')/range-to(id('tok_6980')))"/><!-- chaimVbelVfrereVCeententCVamoiV -->
<mark id="line_450" xlink:href="#xpointer(id('tok_6981')/range-to(id('tok_6995')))"/><!-- volentiersVCVCVoreCediVdeequoiV -->
<mark id="line_451" xlink:href="#xpointer(id('tok_6996')/range-to(id('tok_7012')))"/><!-- coVestdeetonVpruVtantVm'estplusVbelV -->
<mark id="line_452" xlink:href="#xpointer(id('tok_7013')/range-to(id('tok_7026')))"/><!-- nenVfaiVjaVversVdeuVrevelVCV -->
<mark id="line_453" xlink:href="#xpointer(id('tok_7027')/range-to(id('tok_7039')))"/><!-- nenVaezCVenversCVluiVorguilCV -->
<mark id="line_454" xlink:href="#xpointer(id('tok_7040')/range-to(id('tok_7055')))"/><!-- joVtenchastiVCVjoVbienVleevoilV -->
<mark id="line_455" xlink:href="#xpointer(id('tok_7056')/range-to(id('tok_7071')))"/><!-- creezVCVmonVconseilVCValomsCVoffrirCV -->
<mark id="line_456" xlink:href="#xpointer(id('tok_7072')/range-to(id('tok_7086')))"/><!-- adampnedeuVCeCVporVluiVplaisirVCV -->
<mark id="line_457" xlink:href="#xpointer(id('tok_7087')/range-to(id('tok_7098')))"/><!-- silestversVnosVapaiezCVCV -->
<mark id="line_458" xlink:href="#xpointer(id('tok_7099')/range-to(id('tok_7112')))"/><!-- jaVneenusVprendraVCVpecchiezVCV -->
<mark id="line_459" xlink:href="#xpointer(id('tok_7113')/range-to(id('tok_7128')))"/><!-- neesorVnusVneevendraVCVtristorVCV -->
<mark id="line_460" xlink:href="#xpointer(id('tok_7129')/range-to(id('tok_7144')))"/><!-- multVfaitVbonVporchacerVCVCVsamorCV -->
<mark id="line_461" xlink:href="#xpointer(id('tok_7145')/range-to(id('tok_7156')))"/><!-- alomsCVoffrirCVasonValtierCV -->
<mark id="line_462" xlink:href="#xpointer(id('tok_7157')/range-to(id('tok_7173')))"/><!-- telVdonVqueeilvoilleVCeregarderVCVCV -->
<mark id="line_463" xlink:href="#xpointer(id('tok_7174')/range-to(id('tok_7188')))"/><!-- preomVVluiVquilnusVdoinstVsamorCV -->
<mark id="line_464" xlink:href="#xpointer(id('tok_7189')/range-to(id('tok_7206')))"/><!-- enusVdefendeVCVCedeemalVnoitVejorV -->
<mark id="line_465" xlink:href="#xpointer(id('tok_7207')/range-to(id('tok_7222')))"/><!-- belVfrereVCeabelCVmultVasbienVditV -->
<mark id="line_466" xlink:href="#xpointer(id('tok_7223')/range-to(id('tok_7235')))"/><!-- icestCVsermonVCVasbienVescritCV -->
<mark id="line_467" xlink:href="#xpointer(id('tok_7236')/range-to(id('tok_7250')))"/><!-- ejoVcreraiVCVbienVtonVsermonVCV -->
<mark id="line_468" xlink:href="#xpointer(id('tok_7251')/range-to(id('tok_7263')))"/><!-- alomCVoffrirCVbienVestraisonVCV -->
<mark id="line_469" xlink:href="#xpointer(id('tok_7264')/range-to(id('tok_7278')))"/><!-- quoiVoffrirasCVCVtuVjoVunaignelCV -->
<mark id="line_470" xlink:href="#xpointer(id('tok_7279')/range-to(id('tok_7293')))"/><!-- tuitVleemeillorVCVeleeplusVbelV -->
<mark id="line_471" xlink:href="#xpointer(id('tok_7294')/range-to(id('tok_7308')))"/><!-- queeporraiVCVtroverVCVal'ostelCV -->
<mark id="line_472" xlink:href="#xpointer(id('tok_7309')/range-to(id('tok_7321')))"/><!-- icelCVoffriraiCVCVnenfraiVel -->
<mark id="line_473" xlink:href="#xpointer(id('tok_7322')/range-to(id('tok_7333')))"/><!-- siVluiVoffriraiCVCVencensCV -->
<mark id="line_474" xlink:href="#xpointer(id('tok_7334')/range-to(id('tok_7347')))"/><!-- orvusVaiditVtotVmonVporpensVCV -->
<mark id="line_475" xlink:href="#xpointer(id('tok_7348')/range-to(id('tok_7364')))"/><!-- tuVqueeoffrirasCVCVjoVdeemonVbléV -->
<mark id="line_476" xlink:href="#xpointer(id('tok_7365')/range-to(id('tok_7379')))"/><!-- itelCVcumVdeusVleem'adonéVCV -->
<mark id="line_477" xlink:href="#xpointer(id('tok_7380')/range-to(id('tok_7394')))"/><!-- iertdelVmeillorVCVnenilVCVporVvoirV -->
<mark id="line_478" xlink:href="#xpointer(id('tok_7395')/range-to(id('tok_7407')))"/><!-- deecelVfraiVjoVpainValsoirV -->
<mark id="line_479" xlink:href="#xpointer(id('tok_7408')/range-to(id('tok_7425')))"/><!-- telVoffrendeCVCenestpasVaceptableCVCVCe -->
<mark id="line_480" xlink:href="#xpointer(id('tok_7426')/range-to(id('tok_7434')))"/><!-- jaVestcoVfableVCe -->
<mark id="line_481" xlink:href="#xpointer(id('tok_7435')/range-to(id('tok_7448')))"/><!-- richesVCehomesemultVasbestesVCe -->
<mark id="line_482" xlink:href="#xpointer(id('tok_7449')/range-to(id('tok_7469')))"/><!-- siVaiporVqueiVneecontesVCetoitVparVtestesVCe -->
<mark id="line_483" xlink:href="#xpointer(id('tok_7470')/range-to(id('tok_7486')))"/><!-- edeetotesVCedonezVCVlasVdismesVCe -->
<mark id="line_484" xlink:href="#xpointer(id('tok_7487')/range-to(id('tok_7500')))"/><!-- siVoffrirasCVCVadeuVmaimesVCe -->
<mark id="line_485" xlink:href="#xpointer(id('tok_7501')/range-to(id('tok_7513')))"/><!-- offrezCVleeluiVdeebonVcuerV -->
<mark id="line_486" xlink:href="#xpointer(id('tok_7514')/range-to(id('tok_7527')))"/><!-- siVrecevrasVCeCVbonVluerVCV -->
<mark id="line_487" xlink:href="#xpointer(id('tok_7528')/range-to(id('tok_7544')))"/><!-- frasVleetuVensiCVoroezCVfurorVCV -->
<mark id="line_488" xlink:href="#xpointer(id('tok_7545')/range-to(id('tok_7560')))"/><!-- deedisVneeremaindrontVCVCVqueenoefV -->
<mark id="line_489" xlink:href="#xpointer(id('tok_7561')/range-to(id('tok_7574')))"/><!-- icistCVconseilVCVneevealtVVunoef -->
<mark id="line_490" xlink:href="#xpointer(id('tok_7575')/range-to(id('tok_7592')))"/><!-- alomCVoffrirCVdeecaVchesconsVCVparVsoiV -->
<mark id="line_491" xlink:href="#xpointer(id('tok_7593')/range-to(id('tok_7605')))"/><!-- quilvoldraVCVejoVl'otreiCV -->
<mark id="line_492" xlink:href="#xpointer(id('tok_7606')/range-to(id('tok_7621')))"/><!-- belVfrereVCeabelCVissumCVcaVforsV -->
<mark id="line_493" xlink:href="#xpointer(id('tok_7622')/range-to(id('tok_7637')))"/><!-- porVquoiVporVdeporterVCVCVnosVcorsV -->
<mark id="line_494" xlink:href="#xpointer(id('tok_7638')/range-to(id('tok_7654')))"/><!-- eporVreguarderVCVCVnostreVCelaborVCV -->
<mark id="line_495" xlink:href="#xpointer(id('tok_7655')/range-to(id('tok_7668')))"/><!-- cumVsuntVcreuVVsilsuntVemflorV -->
<mark id="line_496" xlink:href="#xpointer(id('tok_7669')/range-to(id('tok_7677')))"/><!-- asprezVpuisVenirrumsCV -->
<mark id="line_497" xlink:href="#xpointer(id('tok_7678')/range-to(id('tok_7692')))"/><!-- plusVleegierVVCVaprésCVenserromsVCV -->
<mark id="line_498" xlink:href="#xpointer(id('tok_7693')/range-to(id('tok_7709')))"/><!-- joVirraiCVovecCVtoiVoutuVvoldrasVCV -->
<mark id="line_499" xlink:href="#xpointer(id('tok_7710')/range-to(id('tok_7721')))"/><!-- orenvienVdoncVbonVleefrasV -->
</markList>
</paula>